dbmig/__init__.py
dbmig/main.py
dbmig-1.7.1.dist-info/METADATA
dbmig-1.7.1.dist-info/WHEEL
dbmig-1.7.1.dist-info/entry_points.txt
dbmig-1.7.1.dist-info/top_level.txt
dbmig-1.7.1.dist-info/RECORD
